{
    "label": "Direction Is Rear-Side Light",
    "label_name": "direction_is_rear_side",
    "def_question": [
        "Is the subject consistently illuminated by a mix of back and side lighting?"
    ],
    "alt_question": [
        "Does the primary light source come from behind and slightly to the side of the subject?",
        "Is the subject lit from a rear-side angle, creating strong contrast?",
        "Does the lighting emphasize both back and side illumination on the subject?",
        "Is there rim lighting from behind while also partially lighting the side of the subject?",
        "Does the subject receive directional lighting from both the back and the side?",
        "Is the main illumination positioned between backlight and sidelight?",
        "Does the shot feature a blend of back and side lighting on the subject?",
        "Is the subject framed with lighting that wraps from the rear and the side?"
    ],
    "def_prompt": [
        "The subject is consistently illuminated by a mix of back and side lighting."
    ],
    "alt_prompt": [
        "A video where the subject is lit from both behind and the side.",
        "A shot featuring strong directional lighting from a rear-side angle.",
        "A sequence where backlight and sidelight work together to shape the subject.",
        "A video where the lighting creates rim highlights while illuminating the side.",
        "A scene where the primary light source is positioned between back and side.",
        "A subject illuminated with a mix of back and side lighting for depth.",
        "A shot emphasizing contrast with both rear and side illumination.",
        "A composition using a lighting blend between back and side sources."
    ],
    "pos_rule_str": "self.lighting_setup.direction_is_rear_side is True",
    "neg_rule_str": "self.lighting_setup.direction_is_rear_side is False",
    "easy_neg_rule_str": {},
    "hard_neg_rule_str": {}
}
